three_play/__init__.py
three_play/constants.py
three_play/errors.py
three_play/log.py
three_play/config/__init__.py
three_play/config/requests.py
three_play/utils/__init__.py
three_play/utils/response.py
three_play/utils/time_util.py
three_play/utils/types.py
three_play/utils/parse/__init__.py
three_play/utils/parse/models.py
three_play/utils/parse/srt.py
three_play/utils/parse/types.py
three_play/v3/__init__.py
three_play/v3/api.py
three_play/v3/helper.py
three_play/v3/models/__init__.py
three_play/v3/models/requests.py
three_play/v3/models/three_play_media.py
three_play-0.1.1.dist-info/LICENSE
three_play-0.1.1.dist-info/METADATA
three_play-0.1.1.dist-info/WHEEL
three_play-0.1.1.dist-info/top_level.txt
three_play-0.1.1.dist-info/RECORD
