Metadata-Version: 2.1
Name: three-play
Version: 0.1.1
Summary: A Python wrapper library for the 3Play API v3
Home-page: https://github.com/rnag/three-play
Author: Ritvik Nag
Author-email: rv.kvetch@gmail.com
License: MIT license
Keywords: three play,threeplay,3play,3play api v3
Platform: UNKNOWN
Classifier: Development Status :: 2 - Pre-Alpha
Classifier: Intended Audience :: Developers
Classifier: License :: OSI Approved :: MIT License
Classifier: Natural Language :: English
Classifier: Programming Language :: Python :: 3
Classifier: Programming Language :: Python :: 3.7
Classifier: Programming Language :: Python :: 3.8
Classifier: Programming Language :: Python :: 3.9
Classifier: Programming Language :: Python :: 3.10
Requires-Python: >=3.7
License-File: LICENSE
Requires-Dist: requests
